{
  "version": "5",
  "dialect": "pg",
  "entries": [
    {
      "idx": 0,
      "version": "5",
      "when": 1710381058656,
      "tag": "0000_lush_punisher",
      "breakpoints": true
    },
    {
      "idx": 1,
      "version": "5",
      "when": 1713538718611,
      "tag": "0001_careless_chimera",
      "breakpoints": true
    },
    {
      "idx": 2,
      "version": "5",
      "when": 1713540605247,
      "tag": "0002_mysterious_stardust",
      "breakpoints": true
    },
    {
      "idx": 3,
      "version": "5",
      "when": 1713540966772,
      "tag": "0003_little_lord_tyger",
      "breakpoints": true
    }
  ]
}